_positional_defaults.py
positional_defaults.py
positional_defaults-2023.4.19.dist-info/LICENSE.txt
positional_defaults-2023.4.19.dist-info/METADATA
positional_defaults-2023.4.19.dist-info/WHEEL
positional_defaults-2023.4.19.dist-info/top_level.txt
positional_defaults-2023.4.19.dist-info/RECORD
