Metadata-Version: 2.1
Name: positional-defaults
Version: 2023.4.19
Summary: Set defaults for any positional-only parameter
Author-email: Nicolas Tessore <n.tessore@ucl.ac.uk>, Nathaniel Starkman <n.starkman@mail.utoronto.ca>
License: MIT
Project-URL: Homepage, https://github.com/ntessore/positional_defaults
Project-URL: Issues, https://github.com/ntessore/positional_defaults/issues
Classifier: License :: OSI Approved :: MIT License
Classifier: Programming Language :: Python :: 3
Requires-Python: >=3.8
License-File: LICENSE.txt
